pybryt/__init__.py
pybryt/__main__.py
pybryt/cli.py
pybryt/complexities.py
pybryt/complexity.py
pybryt/debug.py
pybryt/invariants.py
pybryt/plagiarism.py
pybryt/reference.py
pybryt/student.py
pybryt/utils.py
pybryt/version.py
pybryt/annotations/__init__.py
pybryt/annotations/annotation.py
pybryt/annotations/collection.py
pybryt/annotations/import_.py
pybryt/annotations/initial_condition.py
pybryt/annotations/invariants.py
pybryt/annotations/relation.py
pybryt/annotations/structural.py
pybryt/annotations/type_.py
pybryt/annotations/value.py
pybryt/annotations/complexity/__init__.py
pybryt/annotations/complexity/annotation.py
pybryt/annotations/complexity/complexities.py
pybryt/execution/__init__.py
pybryt/execution/complexity.py
pybryt/execution/memory_footprint.py
pybryt/execution/tracing.py
pybryt/execution/utils.py
pybryt/integrations/__init__.py
pybryt/integrations/otter.py
pybryt/preprocessors/__init__.py
pybryt/preprocessors/abstract_preprocessor.py
pybryt/preprocessors/imports.py
pybryt/preprocessors/intermediate_variables.py
tests/__init__.py
tests/test_cli.py
tests/test_complexity.py
tests/test_debug.py
tests/test_reference.py
tests/test_student.py
tests/test_utils.py
tests/utils.py
tests/annotations/__init__.py
tests/annotations/structural_helpers.py
tests/annotations/test_annotation.py
tests/annotations/test_collection.py
tests/annotations/test_complexity.py
tests/annotations/test_import_.py
tests/annotations/test_initial_condition.py
tests/annotations/test_invariants.py
tests/annotations/test_relation.py
tests/annotations/test_structural.py
tests/annotations/test_type_.py
tests/annotations/test_value.py
tests/annotations/utils.py
tests/execution/__init__.py
tests/execution/test_complexity.py
tests/execution/test_memory_footprint.py
tests/execution/test_notebook_execution.py
tests/execution/test_tracing.py
tests/execution/utils.py
tests/integrations/__init__.py
tests/integrations/test_otter.py
tests/preprocessors/__init__.py
pybryt-0.7.0.dist-info/LICENSE
pybryt-0.7.0.dist-info/METADATA
pybryt-0.7.0.dist-info/WHEEL
pybryt-0.7.0.dist-info/entry_points.txt
pybryt-0.7.0.dist-info/top_level.txt
pybryt-0.7.0.dist-info/RECORD
