Metadata-Version: 2.1
Name: pybryt
Version: 0.7.0
Summary: Python auto-assessment library
Home-page: https://github.com/microsoft/pybryt
Author: Chris Pyles
Author-email: pybryt-support@microsoft.com
License: MIT
Platform: UNKNOWN
Classifier: Programming Language :: Python :: 3
Classifier: License :: OSI Approved :: MIT License
Classifier: Operating System :: OS Independent
Requires-Dist: IPython
Requires-Dist: nbconvert
Requires-Dist: nbformat
Requires-Dist: numpy
Requires-Dist: pandas
Requires-Dist: dill
Requires-Dist: click
Requires-Dist: astunparse
Requires-Dist: Cython
Requires-Dist: ipykernel
